pystreaming/__init__.py
pystreaming/audio/__init__.py
pystreaming/audio/patterns.py
pystreaming/audio/tape.py
pystreaming/listlib/__init__.py
pystreaming/listlib/circulardict.py
pystreaming/listlib/circularlist.py
pystreaming/stream/__init__.py
pystreaming/stream/handlers.py
pystreaming/stream/interface.py
pystreaming/stream/patterns.py
pystreaming/video/__init__.py
pystreaming/video/collect.py
pystreaming/video/dec.py
pystreaming/video/device.py
pystreaming/video/dist.py
pystreaming/video/enc.py
pystreaming/video/pub.py
pystreaming/video/req.py
pystreaming/video/sub.py
pystreaming/video/testimages/__init__.py
tests/__init__.py
tests/test_datstructures.py
tests/test_startstop.py
tests/test_testimages.py
pystreaming-1.3.2.dist-info/LICENSE
pystreaming-1.3.2.dist-info/METADATA
pystreaming-1.3.2.dist-info/WHEEL
pystreaming-1.3.2.dist-info/top_level.txt
pystreaming-1.3.2.dist-info/RECORD
