Metadata-Version: 2.1
Name: pystreaming
Version: 1.3.2
Summary: Video + Audio streaming done with ZMQ
Home-page: https://github.com/joseph-x-li/pystreaming
Author: Joseph Li
Author-email: jxli@andrew.cmu.edu
License: UNKNOWN
Platform: UNKNOWN
Classifier: Programming Language :: Python :: 3.6
Classifier: Programming Language :: Python :: 3.7
Classifier: Programming Language :: Python :: 3.8
Classifier: Programming Language :: Python :: 3.9
Classifier: License :: OSI Approved :: MIT License
Classifier: Operating System :: MacOS
Classifier: Operating System :: Unix
Requires-Python: >=3.6
Requires-Dist: numpy
Requires-Dist: pyzmq
Requires-Dist: PyTurboJPEG
